{"id":"WriteLog","resource_id":"WriteLog","metadata":{"plugin_key":"WriteLog","aliases":["Log"],"summary":"The `WriteLog` plugin logs information during the execution of automation scripts, aiding in debugging, tracking the flow of execution, and recording important information.","description":"The `WriteLog` plugin is designed to write log messages during the execution of automation scripts. It is particularly useful for debugging, tracking the flow of execution, and recording important information.\n\n### Key Features and Functionality\n\n| Feature             | Description                                                                                     |\n|---------------------|-------------------------------------------------------------------------------------------------|\n| Logging Information | Logs the content of the `Argument` property to the log using the logging framework.             |\n| Debugging Aid       | Helps in understanding the flow of automation, capturing important events, or debugging issues. |\n\n### Usages in RPA\n\n| Usage               | Description                                                            |\n|---------------------|------------------------------------------------------------------------|\n| Execution Tracking  | Track the flow of execution by logging key points in the automation.   |\n| Debugging           | Capture log messages to help debug issues in the automation process.   |\n| Information Logging | Record important information during the execution of automation tasks. |\n\n### Usages in Automation Testing\n\n| Usage               | Description                                                                             |\n|---------------------|-----------------------------------------------------------------------------------------|\n| Test Execution Logs | Capture logs during test execution to understand the flow and state of tests.           |\n| Debugging Tests     | Log messages to help debug test failures or unexpected behavior during automated tests. |\n| Recording Test Data | Log test data and results for analysis and verification purposes.","key_parameters":{},"key_properties":{"Argument":{"description":"Specifies the message or information to be logged. This can be a static message or a dynamic value retrieved from parameters.","mandatory":true,"multiple":false,"type":"String|Expression"}},"output_parameters":{},"use_cases":["Logging messages during automation script execution","Debugging automation processes","Tracking execution flow in RPA","Capturing test execution logs","Recording test data for analysis"],"version":"1.0","clstype":"Action"},"examples":[{"description":"Logs a simple message during the execution of the automation script.","rule":{"argument":"Logging a simple message","clearLinesBreak":false,"pluginName":"WriteLog","trim":false}},{"description":"Logs the value of a dynamic parameter during the execution of the automation script.","rule":{"argument":"{{$Get-Parameter --Name:MyParam --Scope:Session}}","clearLinesBreak":false,"pluginName":"WriteLog","trim":false}}],"text":"The `WriteLog` plugin logs information during the execution of automation scripts, aiding in debugging, tracking the flow of execution, and recording important information. Logs a simple message during the execution of the automation script. Logs the value of a dynamic parameter during the execution of the automation script.","embedding":[-0.017919445,0.013017088,0.01324754,-0.015489217,-0.0128704365,0.028422505,-0.02328271,-0.013680512,0.03002869,-0.026606817,0.020028438,0.023869317,-0.00016029122,-0.010482108,-0.009504429,-0.01318469,0.021899993,-0.013296424,0.027361024,-0.009888518,-0.01459534,0.00081793265,0.002955731,0.002152638,-0.005701959,0.0068367645,-0.018296551,-0.038911596,0.00932286,0.01181594,0.018045148,-0.026648717,-0.0018121966,-0.015559051,-0.0002970134,0.0063269753,-0.021927927,0.0142461695,0.022486601,-0.011494704,0.041341823,0.029302415,-0.00004713806,-0.01913456,0.000555618,0.03818532,-0.003697719,-0.032738257,-0.036844503,0.000879474,-0.008247415,-0.01152962,-0.046900623,-0.004176083,0.021536855,0.0028073334,0.04519667,0.0015503184,0.011459786,-0.022640236,-0.005918445,-0.0014682632,-0.01574062,-0.00787031,-0.0014185064,-0.0043367017,-0.013624645,0.010754461,0.007535106,-0.012241929,0.009232076,0.011431852,-0.0008428111,-0.013233574,0.0124025475,-0.0042878175,-0.019469764,0.0026519522,0.019008858,0.008072829,0.011857841,0.010468141,-0.02142512,0.040056877,0.013191673,-0.014441704,0.0079890285,0.019260261,-0.038157385,-0.020335708,0.01864572,0.004116724,0.017374739,0.02129942,0.021480989,-0.01038434,-0.0023778533,0.038073584,0.000353099,-0.021145785,0.0045392206,0.0018733015,-0.043716185,0.0044519277,-0.04047588,-0.023617914,0.00533533,0.0020566161,0.036397565,-0.011739123,-0.0280873,0.044414528,0.024539724,-0.022542467,-0.012193045,0.03726351,0.03871606,-0.034023203,-0.040615547,-0.022696102,0.015559051,0.013722413,0.032291315,-0.0018663179,0.019218361,0.0028090791,0.008498818,-0.001051877,-0.0073395707,-0.013806214,0.016383095,-0.012912337,0.01764011,-0.0061558816,-0.011110615,0.014525506,-0.03681657,0.0032961725,-0.022598336,-0.008568652,0.030252159,0.029330349,-0.01913456,0.020698845,-0.03796185,0.0056670425,-0.0077236583,-0.0071719685,0.03072703,-0.010510041,-0.008387083,-0.01011897,0.013031054,-0.014679141,-0.006470135,0.019455798,0.026173845,-0.009169226,-0.0047557065,-0.021899993,0.011969576,0.034889147,-0.02005637,-0.0046963473,0.025419636,0.03553162,0.0076957247,0.00078039675,-0.03033596,-0.023967085,-0.0028684381,0.015279715,-0.033548333,0.002571643,-0.02301734,0.032151647,-0.0067529636,-0.0034026694,0.020601077,0.02328271,0.033967335,0.014127451,-0.014623273,0.033436596,-0.027766064,0.0015695228,0.008764188,0.012262879,-0.01291932,0.025992276,-0.0039770557,0.020210007,-0.0048185573,-0.0039316635,-0.60202634,-0.023129074,-0.012095277,-0.017374739,0.016802099,0.01314279,-0.020489343,0.023198908,-0.012137177,0.014441704,0.017332839,0.010859212,0.010607809,0.0031425373,-0.0012596337,-0.012528249,-0.013624645,-0.03963787,-0.026704583,0.007905227,0.0015511913,0.03268239,-0.038911596,-0.009455546,-0.0043227347,-0.009183193,0.010866196,0.008470884,0.008366133,0.031062236,-0.028366636,-0.006113981,-0.026299546,0.011452802,0.04148149,0.010754461,-0.007500189,-0.012570149,-0.0056670425,0.040811084,-0.019302163,-0.024064852,-0.009022574,0.0011077444,0.018352417,0.009923435,0.038520522,-0.024777161,0.00265719,-0.023771549,0.014316003,0.0039526136,0.0018925058,0.015894255,0.0017659314,0.022346932,0.015838388,-0.0064561684,0.015642852,0.0010317997,-0.020475376,-0.0074722553,-0.004724281,0.018966958,-0.0028911342,0.0008270984,0.006103506,-0.012241929,-0.021662557,-0.0116972225,0.0015197659,-0.006948499,0.0036732769,-0.01294027,0.017961347,0.003254272,0.044721797,0.01011897,-0.0008275348,0.004940767,0.008889888,-0.027556561,-0.04701236,-0.032514784,0.02778003,0.013736379,-0.004444944,-0.032822058,0.010070086,0.009769799,0.03284999,0.042263635,-0.016704332,-0.026914086,-0.013045021,0.012716801,-0.005810202,0.007926177,-0.02138322,-0.0007467891,-0.017430607,0.01768201,-0.0038723042,0.013575762,0.033939403,0.02690012,0.014846743,-0.011417885,0.037794247,-0.040559683,0.010461157,-0.009881534,-0.0061663566,0.0009942639,-0.011103632,-0.03125777,0.017486474,-0.027682262,0.04863251,-0.034861214,0.02226313,-0.012493332,0.018296551,0.014385837,0.020531245,0.018184816,0.01574062,-0.0066586873,-0.0032699846,-0.020992149,0.0032158631,0.018883158,0.011941642,-0.004403044,-0.02271007,-0.009665048,0.019008858,-0.0041690995,0.014567406,-0.0071929186,-0.05670534,0.019511664,-0.0068367645,-0.023925183,0.0065225107,-0.040978685,-0.02046141,0.0021351795,0.0109988805,-0.000098149736,0.0048604575,-0.023562046,-0.01931613,0.032375116,-0.03575509,-0.010412274,0.0062955497,-0.023240808,0.006770422,-0.047990035,-0.006735505,0.04405139,0.0016786386,-0.018994892,-0.013289441,-0.010356407,-0.013038038,0.010489091,-0.0128494855,-0.024623526,0.015042279,0.004448436,0.020391576,-0.0063095167,0.034777414,0.017360773,-0.014295053,-0.005694976,0.010656693,-0.0091412915,-0.026732517,0.031285703,-0.0064177597,-0.013666546,0.052040417,-0.0026746483,0.016215492,0.04977779,-0.026592849,0.011166482,-0.025740873,0.015992023,-0.0005643473,-0.017821679,-0.028282836,0.03863226,-0.016173592,0.003865321,0.00084892154,0.03416287,0.020433476,0.027151523,0.0009864075,-0.03695624,0.0027601952,-0.0020548701,0.0030447694,-0.029777287,0.041984297,0.019735135,0.0024005494,-0.018575888,-0.01798928,-0.001937898,0.026020208,-0.015335582,0.0025332342,0.020307774,0.014916577,0.005660059,0.027333092,-0.010845246,0.034498077,-0.018994892,-0.014832776,0.016969701,0.031592976,0.028799608,0.014455671,-0.016760198,0.01772391,0.006319992,0.011271234,-0.01375733,0.017486474,0.011767057,0.011669288,-0.03505675,0.023520146,0.011585488,-0.024064852,0.00031840013,0.03866019,-0.013380226,0.00330141,-0.006093031,0.018156882,-0.00504901,-0.028939277,-0.013149773,0.0071859355,-0.005897495,0.0028981178,-0.013903982,0.02195586,0.0029452557,-0.0024145162,-0.0072278357,0.03268239,0.017374739,0.013624645,0.004221475,-0.005024568,-0.00203392,0.02301734,-0.027626395,-0.024721293,-0.0059917714,-0.01939993,-0.013917948,0.0036907354,0.003708194,0.023576014,-0.01009802,0.02724929,0.001220352,0.018547954,0.057766818,-0.0062501575,-0.0044100275,0.00053554075,-0.027277224,0.004448436,-0.0019937654,0.01463724,-0.0393306,-0.046062615,0.012109243,-0.0060685887,0.019022826,0.008924806,0.010824295,-0.000328657,0.00016367382,0.042235702,0.015028312,0.029470017,-0.0062396824,0.005464523,0.0010702085,-0.010852229,0.019944636,0.0051747113,-0.015908223,0.02271007,0.025266,-0.025349801,-0.03139744,-0.007926177,-0.016857967,0.009790749,-0.006103506,-0.012633,-0.023743615,0.00010044117,0.026536983,0.010139921,0.009092408,0.0012037663,0.027752096,-0.00547849,-0.009783766,-0.012311763,0.02332461,0.0074024214,0.011250284,0.020894382,0.007947127,-0.019232329,-0.014113484,-0.026997887,-0.009057491,0.028003499,0.022235198,-0.0023342068,0.014295053,0.0147070745,0.0036802604,-0.0021281962,-0.015726654,-0.00811473,-0.041034553,0.012605066,-0.018813323,0.0016795116,-0.017598208,-0.0076608076,0.0054854737,0.011089665,0.0013425618,0.008428983,0.0052724793,-0.029442083,-0.03276619,0.00041420388,0.045252535,0.03399527,0.011473753,-0.008463901,0.06413569,0.019022826,0.009965335,0.013624645,-0.0076608076,0.002418008,0.009797733,-0.0024424498,-0.02275197,-0.002714803,-0.03567129,-0.005537849,0.013554811,0.014874676,0.010475124,0.02336651,-0.011445819,-0.014762942,0.0060546217,-0.001805213,0.026592849,0.012458415,0.006061605,-0.025363768,-0.013631629,-0.022360899,-0.011885774,0.012227962,-0.02420452,-0.038827796,0.0042633754,-0.00035200783,0.01316374,-0.02279387,0.013931915,0.017472507,0.0031495208,-0.05648187,0.0009750595,0.037403177,0.011983543,-0.0064282347,-0.00727672,-0.0073744874,0.007549073,0.008582619,-0.043101646,-0.0006686621,-0.028967211,-0.0050420268,0.009043524,-0.0084569175,0.020335708,-0.043380983,0.016871933,0.0049931426,0.011131565,0.007807459,0.0009340319,0.012109243,-0.035699222,-0.00080221996,0.014818809,0.035084683,0.00574386,0.009294927,-0.052403554,0.000055512704,-0.016411029,-0.002477367,0.007863327,-0.01353386,0.014162368,-0.011180449,-0.019902736,0.017849611,0.015964089,0.010607809,0.006365384,0.026006242,0.032430984,0.005132811,-0.007786509,-0.01882729,-0.002152638,-0.00037688625,-0.03561542,0.036313765,0.006400301,0.0051537612,0.012130194,0.023925183,-0.023967085,0.0030430236,0.024665426,0.010510041,-0.0069554825,-0.01935803,0.0012997884,-0.0006699715,-0.0021858092,-0.00067215384,-0.00819853,-0.02831077,-0.0061768317,0.012779652,0.028827542,0.02579674,0.016452929,0.03589476,-0.027277224,0.0076398575,0.018450186,0.013498943,0.04854871,0.015559051,-0.03796185,-0.016411029,-0.025936408,-0.017221104,-0.017654076,0.0049233083,0.020838514,0.013191673,0.0018767931,0.033688,-0.003507421,0.010572893,-0.009420629,0.0038583374,0.013394193,0.006375859,-0.003984039,0.011864824,0.005241054,-0.008589602,0.0017729148,0.010510041,0.011194416,0.0076747746,0.0028981178,-0.013938899,0.0028143167,0.006281583,-0.014371871,-0.009434596,0.031509176,0.0037116858,-0.008652452,-0.02187206,-0.021327354,-0.0075071724,0.016215492,-0.014958478,-0.007112609,0.032291315,-0.014260136,0.019162495,0.001974561,-0.0014254898,-0.036006495,0.0063130083,-0.042431235,0.0045147785,0.027402926,0.030391827,0.012807585,-0.0064456933,-0.005984788,-0.007786509,0.014735009,-0.025307901,0.007381471,0.012465398,-0.012542215,-0.02363188,-0.016592598,0.009176209,0.0065853614,0.020670911,-0.0041132323,-0.009692982,0.0011444073,0.00014195975,-0.02583864,-0.006567903,-0.03134157,0.028562173,0.022905605,0.01776581,0.031062236,-0.008184564,-0.019777035,-0.0112433005,-0.00076468405,-0.027500693,-0.0051886784,0.037319377,-0.012465398,-0.023883283,-0.001698716,0.008729271,0.022193298,-0.014986412,0.004877916,0.015908223,-0.03567129,-0.023799483,0.008561668,-0.013827164,0.022654202,0.0075630397,0.009176209,0.007570023,0.008016962,-0.042123966,0.008645469,-0.01702557,0.02134132,-0.008631502,0.017961347,-0.0018837765,0.0062641245,-0.015559051,-0.0005708943,-0.018059114,-0.0024791127,0.003900238,0.014078567,-0.0018366384,0.013100889,-0.0008218608,-0.040364146,-0.0103075225,0.029414149,-0.025768805,0.036146164,0.020559177,0.00069659576,0.018394317,-0.020126205,-0.012884403,-0.008240432,-0.011983543,0.020992149,0.009113358,-0.0071719685,0.012486348,-0.013924932,-0.00330141,-0.0021508923,0.004507795,-0.0015686499,0.008743237,-0.029051011,-0.0119346585,-0.015559051,0.028771674,0.021103883,0.008310265,-0.009106374,0.031592976,0.028799608,-0.04092282,-0.0020915333,-0.024651458,-0.010125954,0.0014918323,-0.02222123,0.011396935,-0.037095908,0.009511413,0.0060371635,-0.04740343,-0.009867568,0.008387083,0.0022469142,0.002438958,0.0071195927,0.009120341,0.0035440838,0.011976559,0.006494577,0.010524008,0.004664922,-0.001219479,-0.034972947,0.035000883,0.0046719057,0.0011426614,0.0050455183,-0.004556679,0.011669288,-0.024455924,0.010223721,0.0046020714,-0.00069354055,0.0067040795,-0.0022626268,0.0037640613,-0.012255896,-0.008715304,0.042319503,0.021508923,-0.021271486,-0.027053755,-0.012025443,-0.0013539098,0.02438609,0.005527374,-0.03435841,-0.009972318,-0.027095655,-0.05282256,0.0024843502,-0.0076398575,0.044889398,-0.003697719,0.01181594,-0.01905076,-0.023003373,-0.00033651336,-0.012744735,0.0011042526,-0.009357777,0.018296551,0.009113358,-0.005646092,0.019749101,-0.01741664,0.013198657,-0.034498077,-0.0016079316,0.011362018,-0.0021351795,-0.010433224,-0.02076868,-0.003540592,-0.0052201035,0.0068856482,-0.012381597,-0.004273851,0.017933413,0.0029417642,-0.030363893,-0.014665174,-0.003826912,-0.0028597089,-0.016089791,-0.00027999133,-0.03947027,-0.018771423,0.022779904,-0.016983667,-0.006508544,-0.00017960474,0.019064726,-0.0052340706,0.0034759955,-0.019679267,-0.012172095,-0.004916325,-0.01856192,-0.0036069346,0.0021578756,0.020796614,0.026802352,0.012276846,0.03810152,-0.014281087,0.014609307,-0.002524505,0.004773165,0.014455671,-0.0038408788,-0.009183193,0.00758399,-0.0038094535,0.0079820445,-0.0025611678,-0.008736254,0.024833027,-0.046593353,0.009043524,-0.0036034428,-0.03572716,0.002466892,-0.028743742,-0.014057617,-0.0034044154,-0.015447317,-0.008470884,0.01776581,-0.001458661,0.011145532,-0.008345182,-0.0011924183,0.009169226,0.009001624,-0.017179204,0.013289441,0.18123361,-0.00038234203,-0.014804843,0.015209881,-0.0030534987,0.030950502,-0.023310643,-0.009294927,-0.013715429,0.014343937,0.037542846,-0.007716675,-0.01236763,0.012095277,-0.01794738,-0.01463724,-0.005052502,-0.018045148,-0.016676398,0.00039216247,0.009518396,-0.009176209,-0.0051886784,-0.011522637,0.05092307,0.003540592,0.020126205,-0.0015241306,0.023925183,0.028157134,-0.01935803,-0.021089917,0.0033049018,-0.015321615,0.00088951265,-0.02716549,0.004102757,-0.013219607,0.0168859,-0.0019117102,0.0033799734,0.000020977528,-0.023436345,-0.021676524,0.027891764,0.000038163278,-0.017472507,-0.0060476386,-0.011767057,0.054638248,-0.009902484,0.011711189,0.021034049,0.0280454,0.013296424,0.0058416277,0.00082098786,0.010139921,0.0034882163,0.0070183333,-0.017402673,0.0043646353,-0.022919573,-0.010202771,-0.021592723,0.012765685,-0.016899867,0.003757078,-0.00308667,-0.015475251,-0.002260881,-0.012584116,-0.010963963,0.010440207,-0.014581373,-0.0045741377,0.01351291,0.010000252,0.013715429,-0.0027933666,-0.022640236,-0.026117977,-0.0011173466,-0.024414023,-0.01653673,0.004273851,0.020880414,-0.015586985,-0.02213743,0.0031058744,-0.010496074,-0.022109495,0.0007799603,0.00027191677,0.0019483732,0.0019710693,-0.012772668,-0.0066307536,-0.024260389,-0.015531118,-0.02367378,0.04977779,0.031201905,0.00018036854,-0.0133243585,0.010091037,-0.038157385,0.018715555,-0.006134931,-0.022235198,0.011362018,-0.00043100773,0.010803345,0.0025803724,0.00363836,-0.006288566,0.0010178329,-0.007877294,-0.016089791,0.018198783,0.0035493213,-0.008533735,-0.018813323,0.00643871,0.015028312,0.0016070587,-0.05229182,-0.010845246,-0.013373242,0.008366133,-0.029609686,-0.0077795256,-0.012095277,-0.018212749,0.02050331,-0.006473627,-0.0031495208,-0.00392468,0.0012674901,0.008980674,0.002046141,0.02297544,-0.012241929,-0.016061857,0.01931613,-0.024846995,0.0013477993,0.01582442,-0.013680512,-0.037542846,-0.04092282,-0.00019040721,0.004822049,0.008624519,0.02156479,-0.021117851,-0.031229837,-0.046202283,0.012053376,0.0044589113,-0.045308404,-0.008205514,0.011955609,-0.009246043,-0.012598083,-0.02305924,-0.17676423,0.016969701,0.0098396335,-0.047990035,0.012053376,0.022863705,0.01631326,0.01627136,-0.039358534,0.03717971,-0.011306151,-0.0057752854,-0.05176108,-0.006508544,-0.025070464,0.013903982,0.003051753,0.01710937,0.019385964,0.023198908,0.015950123,-0.013645595,0.0308667,0.020084305,0.02072678,0.0038129452,-0.002966206,-0.014071584,0.01786358,-0.037095908,-0.018813323,0.007961094,-0.023436345,-0.0023429361,-0.0056530754,-0.0028789134,0.0036069346,-0.016341195,-0.004500812,0.016830033,0.01772391,0.025252033,-0.006676146,-0.022961473,0.008701337,0.036118228,-0.002321986,-0.030000756,-0.0023778533,0.01847812,0.015237814,-0.02553137,-0.000016626533,-0.01864572,0.037850115,-0.015559051,-0.0022102513,0.025070464,-0.028464405,0.01486071,0.005562291,-0.028687874,-0.024414023,0.011215366,-0.0038373873,0.0015450808,-0.04251504,0.015098146,-0.013673529,0.02424642,-0.003025565,-0.017542342,-0.014679141,0.003062228,0.0112293335,-0.012884403,-0.01702557,0.005474998,0.010181821,0.009595213,-0.009336827,0.026746484,-0.011417885,-0.011480737,0.008729271,0.033660065,-0.012521265,0.029693486,0.00009525816,-0.01764011,0.0051153526,-0.0067075714,-0.018631754,-0.016955735,-0.010949996,0.007884277,-0.0011225842,0.009155259,0.025782773,-0.00260656,-0.014232202,0.008415016,-0.010181821,-0.0005591098,0.005747352,-0.00047094413,-0.010503058,0.009183193,0.05150968,-0.018631754,-0.051034804,0.03620203,0.0010684627,0.03687244,0.00057351304,0.0077446084,0.00020459227,-0.006407284,-0.010607809,-0.0026641733,0.031984046,-0.0070008747,-0.02716549,0.008875922,-0.019595467,-0.004940767,-0.10514232,-0.014190302,-0.007213869,0.011711189,0.037012108,0.022416767,-0.020964216,0.02508443,0.012248912,-0.011941642,-0.027989533,-0.00729767,0.008827038,-0.021453055,0.033715934,-0.002824792,-0.014776909,-0.009092408,-0.024888895,0.027179455,-0.010614793,-0.020964216,-0.022193298,0.000035844565,0.00013846805,0.0034620287,-0.016844,0.011571521,0.0022172346,-0.0023848366,-0.011138549,-0.0072906865,0.028827542,-0.009246043,0.019609433,-0.002629256,-0.03514055,-0.012674901,0.007430355,-0.016802099,0.013589728,0.017737877,0.029386215,-0.023115108,-0.0089178225,-0.018897124,-0.007688741,0.035028815,-0.012004493,-0.013045021,-0.03284999,0.00094537996,-0.02980522,0.0036767686,0.024414023,-0.043157514,0.01034244,-0.00983265,-0.022402799,0.012926304,-0.025168233,-0.011124582,-0.00844295,0.016871933,-0.01715127,0.0041795745,-0.012542215,0.0025175216,0.024749227,0.0063374504,-0.041118354,0.00603018,0.0068961238,0.009315877,-0.014127451,-0.0067913723,-0.005572766,-0.0027462284,-0.010056119,-0.009211126,-0.0037396194,-0.020028438,0.0046265135,-0.023101142,-0.0009183192,0.011711189,-0.01175309,-0.0105449585,0.0024267372,-0.040978685,-0.009434596,0.024539724,-0.004675397,0.008303282,-0.021089917,-0.009769799,-0.0074443216,-0.019679267,-0.008959723,-0.007144035,-0.011983543,-0.026969954,-0.06318595,-0.004238934,0.0051363027,0.021983795,-0.003718669,-0.04025241,-0.004018956,0.003193167,0.0135617945,-0.0071405433,-0.03447014,0.009720915,0.0046963473,0.0031076202,-0.020098273,-0.0014132689,0.020405542,-0.006756455,0.0022434224,-0.021899993,-0.02271007,-0.02195586,0.015098146,-0.020936282,-0.0031128577,0.0064282347,-0.0045287455,-0.0028893885,-0.016285326,-0.016257392,0.01032149,-0.011348051,0.0014307274,0.036565166,-0.02266817,0.015531118,0.0084569175,0.0032158631,0.020559177,0.016159626,0.007772542,-0.029861087,0.006246666,-0.021746358,0.023813449,0.018869191,0.0035318627,0.021508923,-0.010524008,-0.0036174096,0.039218865,0.003528371,-0.01715127,0.0017275226,-0.0017257767,-0.022514533,-0.011718173,0.0020618537,0.009741866,-0.01177404,0.046900623,-0.0039526136,0.015140046,-0.02972142,0.010370373,-0.013966832,-0.011306151,-0.0065853614,0.017207138,0.007821426,-0.012821552,-0.008484851,0.0055483244,0.014776909,0.042096034,0.02428832,-0.0030534987,0.0055937166,0.009336827,0.022514533,0.027277224,-0.014888643,-0.023394445,0.037095908,0.009916451,0.0128704365,-0.02831077,-0.014343937,0.018589854,-0.003980547,-0.021103883,0.0025629138,-0.01600599,0.030363893,0.0076747746,-0.009797733,-0.015531118,0.02085248,0.022318998,0.01997257,0.0028370128,0.025978308,0.0018471136,-0.01071256,0.0051258276,0.012213995,0.00026580627,-0.00956728,0.032486852,0.02001447,-0.01289837,-0.023953117,0.00003887253,0.017263005,0.0018575888,0.017332839,-0.015126079,-0.021117851,-0.020740746,0.02702582,0.022235198,-0.00729767,0.029330349,-0.028995145,0.03863226,-0.004846491,0.009427612,-0.026076077,0.008282332,-0.0031372998,0.023492211,-0.00817758,-0.03011249,0.018380351,-0.0059359036,0.009134308,-0.036006495,-0.0015782521,0.020475376,0.09514207,0.033464532,-0.004822049,0.019958604,-0.025293933,0.006679638,0.0059987544,0.018184816,0.019707201,-0.009364761,0.023073208,-0.0041132323,-0.004078315,-0.015894255,-0.014343937,-0.0036174096,0.00899464,0.01860382,0.0008393193,-0.003757078,-0.00011839073,0.0063793506,-0.0020513786,0.023031307,-0.023813449,-0.016816067,0.013931915,-0.008247415,-0.024218487,-0.01772391,-0.01097793,0.011341068,-0.012667917,-0.007933161,0.006288566,-0.00031861837,0.0021107376,-0.009860584,0.0048639495,0.033436596,0.008428983,-0.010223721,-0.013701463,-0.029078946,-0.0073884544,0.02628558,-0.0019658317,-0.007842377,-0.008554685]}
